dagster_dataform/__init__.py
dagster_dataform/dataform_orchestration_schedule.py
dagster_dataform/dataform_polling_sensor.py
dagster_dataform/resources.py
dagster_dataform/utils.py
dagster_dataform-0.0.5.dist-info/METADATA
dagster_dataform-0.0.5.dist-info/WHEEL
dagster_dataform-0.0.5.dist-info/top_level.txt
dagster_dataform-0.0.5.dist-info/RECORD
