Metadata-Version: 2.4
Name: dagster-dataform
Version: 0.0.5
Summary: A Dagster integration for Dataform
Requires-Python: >=3.10
Requires-Dist: dagster-webserver>=1.8.12
Requires-Dist: dagster==1.11.4
Requires-Dist: google-cloud-dataform>=0.6.2
